daplug_core/__init__.py
daplug_core/base_adapter.py
daplug_core/dict_merger.py
daplug_core/json_helper.py
daplug_core/logger.py
daplug_core/publisher.py
daplug_core/schema_loader.py
daplug_core/schema_mapper.py
daplug_core/types.py
daplug_core-1.0.0b5.dist-info/licenses/LICENSE
daplug_core-1.0.0b5.dist-info/METADATA
daplug_core-1.0.0b5.dist-info/WHEEL
daplug_core-1.0.0b5.dist-info/top_level.txt
daplug_core-1.0.0b5.dist-info/RECORD
