Metadata-Version: 2.4
Name: daplug-core
Version: 1.0.0b5
Summary: Shared schema, merge, and SNS helpers powering daplug adapters.
Home-page: https://github.com/dual/daplug-core
Author: Paul Cruse III
Author-email: paulcruse3@gmail.com
License: Apache License 2.0
Project-URL: Homepage, https://github.com/dual/daplug-core
Project-URL: Documentation, https://github.com/dual/daplug-core#readme
Project-URL: Source Code, https://github.com/dual/daplug-core
Project-URL: Bug Reports, https://github.com/dual/daplug-core/issues
Project-URL: CI/CD, https://circleci.com/gh/dual/daplug-core
Keywords: daplug,schema,sns,event-driven,database,adapter,python-library
Platform: any
Classifier: Development Status :: 3 - Alpha
Classifier: Environment :: Web Environment
Classifier: Environment :: Console
Classifier: Intended Audience :: Developers
Classifier: License :: OSI Approved :: Apache Software License
Classifier: Operating System :: OS Independent
Classifier: Topic :: Database :: Front-Ends
Classifier: Topic :: Software Development :: Libraries :: Python Modules
Classifier: Programming Language :: Python
Classifier: Programming Language :: Python :: 3
Classifier: Programming Language :: Python :: 3.9
Classifier: Programming Language :: Python :: 3.10
Classifier: Programming Language :: Python :: 3.11
Classifier: Programming Language :: Python :: 3 :: Only
Requires-Python: >=3.9
License-File: LICENSE
Requires-Dist: boto3>=1.34
Requires-Dist: jsonref>=0.2
Requires-Dist: PyYAML>=5.3
Requires-Dist: simplejson>=3.17
Dynamic: author
Dynamic: author-email
Dynamic: classifier
Dynamic: description
Dynamic: description-content-type
Dynamic: home-page
Dynamic: keywords
Dynamic: license
Dynamic: license-file
Dynamic: platform
Dynamic: project-url
Dynamic: requires-dist
Dynamic: requires-python
Dynamic: summary
